{
    "title": "Jero Rm | Web",
    "description": "Bienvenido a mi portafolio, aquí encontrarás información sobre mi experiencia, proyectos y habilidades.",
    "image": "/avatar.png",

    "avatar": "/avatar.png",
    "name": "Jeronimo Ramírez Mejía",
    "skill": "Developer and economist",
    "location": "Colombia",
    "media": {
        "email": "jerodatadev@gmail.com",
        "cv": "/data/cv.pdf",
        "github": "https://github.com/TheHakoDrako",
        "likedin": "https://www.linkedin.com/in/jeronimo-ramirez-mejia/"
    },
    "about": "Soy un economista y desarrollador de software apasionado por la tecnología y la economía. Me gusta aprender cosas nuevas y enfrentar desafíos. Actualmente me encuentro trabajando en proyectos de desarrollo y análisis de datos. Aquí encontrarás información sobre mi experiencia, proyectos y habilidades.",
    "technologies": [
        {
            "icon": "devicon-python-plain",
            "name": "Python"
        },
        {
            "icon": "devicon-bash-plain",
            "name": "Bash"
        },
        {
            "icon": "devicon-matplotlib-plain",
            "name": "R & Stata"
        },
        {
            "icon": "devicon-mysql-plain",
            "name": "SQL"
        },
        {
            "icon": "devicon-html5-plain",
            "name": "HTML"
        },
        {
            "icon": "devicon-css3-plain",
            "name": "CSS"
        },
        {
            "icon": "devicon-javascript-plain",
            "name": "JavaScript"
        },
        {
            "icon": "devicon-react-plain",
            "name": "React"
        },
        {
            "icon": "devicon-nodejs-plain",
            "name": "Node"
        },
        {
            "icon": "devicon-mongodb-plain",
            "name": "MongoDB"
        },
        {
            "icon": "devicon-git-plain",
            "name": "Git"
        },
        {
            "icon": "devicon-php-plain",
            "name": "PHP"
        }
    ],
    "experience": [
        {
            "icon": "briefcase-business",
            "title": "Asistente de proyectos",
            "subtitle": "Futurum Technology",
            "description": "Asesoré proyectos económicos y de ingeniería, realicé análisis de datos y transformación de bases de datos. Además, gestioné proyectos utilizando herramientas como API, Power BI y Excel.",
            "date": "Ago 2023 - Dic 2023"
        },
        {
            "icon": "briefcase-business",
            "title": "Full Stack Developer",
            "subtitle": "GYMAPP",
            "description": "Trabajé en equipo utilizando GIT, desarrollando tanto el frontend como el backend con tecnologías como PHP, HTML, SASS y LARAVEL. Además, manejé bases de datos MySQL y estructura de datos.",
            "date": "Dic 2022 - May 2023"
        },
        {
            "icon": "briefcase-business",
            "title": "Estudiante investigador y Auxiliar de docencia",
            "subtitle": "Universidad del Quindio",
            "description": "Realicé investigación en el programa de economía, así como análisis de datos y bases de datos utilizando Excel avanzado. También realicé prácticas en la Gobernación del Quindío.",
            "date": "Feb 2022 - May 2023"
        },
        {
            "icon": "briefcase-business",
            "title": "Desarrollador junior",
            "subtitle": "SUNNEL 'GREETECH'",
            "description": "Trabajé en equipo utilizando GIT, actualicé código tanto en el frontend como en el backend. Además, contribuí al marketing y desarrollo de software que resultó en una eficiencia del 50%.",
            "date": "Jul 2021 - Ago 2021"
        }
    ],
    "projects": [
        {
            "icon": "folder-input",
            "title": "Mi primera página web",
            "subtitle": "Primer portafolio",
            "description": "Página en la cual aprendi a programar y a desarrollar mis habilidades en el desarrollo web, manejando diferentes estilos y use como framework vite, javascript, html y css.",
            "technologies": [
                {
                    "icon": "devicon-javascript-plain",
                    "name": "JavaScript"
                },
                {
                    "icon": "devicon-html5-plain",
                    "name": "Html"
                },
                {
                    "icon": "devicon-css3-plain",
                    "name": "Css"
                },
                {
                    "icon": "devicon-vitejs-plain",
                    "name": "Vite"
                }
            ],
            "image": "/project_1.png",
            "url": "https://jerodev.work.gd/",
            "github": "https://github.com/TheHakoDrako/thehakodrako.github.io"
        },
        {
            "icon": "folder-input",
            "title": "En desarrollo",
            "subtitle": "Diferentes proyectos",
            "description": "Puedes ver todos mis proyectos en repositorios de github, donde se encuentran en desarrollo y en diferentes etapas de desarrollo.",
            "technologies": [
                {
                    "icon": "devicon-devicon-plain",
                    "name": "Binario"
                }
            ],
            "image": "/project_2.png",
            "url": "https://github.com/TheHakoDrako?tab=repositories",
            "github": "https://github.com/TheHakoDrako"
        }
    ],
    "training": [
        {
            "icon": "graduation-cap",
            "title": "Graduado investigador",
            "subtitle": "Universidad del Quindio",
            "description": "Obtuve el título de economista con mención de honor. Además, realicé investigaciones en el campo de la economía durante mi tiempo en la universidad.",
            "date": "2023",
            "certificate": "https://www.uniquindio.edu.co/"
        },
        {
            "icon": "app-window",
            "title": "Cursos en Platzi",
            "subtitle": "Platzi",
            "description": "Realizo varios cursos en Platzi para mejorar mis habilidades en diversas áreas, incluyendo programación, desarrollo web, análisis de datos, entre otros.",
            "date": "2020 - actualidad",
            "certificate": "http://platzi.com/p/JeroRm/"
        },
        {
            "icon": "app-window",
            "title": "Cursos en Udemy",
            "subtitle": "Udemy",
            "description": "Tomo cursos en Udemy para continuar mi formación en áreas específicas, complementando mi educación universitaria y adquiriendo nuevas habilidades técnicas.",
            "date": "2020 - actualidad",
            "certificate": "https://ibmcsr.udemy.com/?next=%2Fuser%2Fda1f9c52-85dc-4b05-89f3-8e6374abcff8%2F"
        },
        {
            "icon": "app-window",
            "title": "Cursos en IBM",
            "subtitle": "IBM",
            "description": "Participo en cursos ofrecidos por IBM para ampliar mis conocimientos en tecnologías específicas y mejorar mis habilidades en el análisis de datos y la programación.",
            "date": "2020 - actualidad",
            "certificate": "https://ibmcsr.udemy.com/user/da1f9c52-85dc-4b05-89f3-8e6374abcff8/"
        }
    ],
    "extras": [
        {
            "image": "/extra_1.png",
            "title": "Jiu Jitsu",
            "description": "Practico Jiu Jitsu y actualmente estoy compitiendo en torneos del país.",
            "url": "https://todojiujitsu.com/que-es-el-jiu-jitsu/"
        },
        {
            "image": "/extra_2.png",
            "title": "Gym",
            "description": "Parte de mis hábitos diarios es ir al gimnasio y mantenerme en forma.",
            "url": "https://enciclopediaonline.com/es/gimnasio/"
        },
        {
            "image": "/extra_3.png",
            "title": "Lector",
            "description": "Me encanta leer todo tipo de literatura. Mira mi lista de libros y anímate a leerlos.",
            "url": "https://www.buscalibre.com.co/v2/mi-lista-de-libros_1482475_l.html?afiliado=64d3811033224581008e"
        }
    ],
    "quotes": [
        {
            "description": "La economía no es una ciencia exacta, pero es una ciencia que se basa en la lógica y la razón.",
            "author": "Jero Rm"
        },
        {
            "description": "La programación es una habilidad que se puede aprender, pero la pasión por la tecnología es algo que se lleva en la sangre.",
            "author": "Jero Rm"
        },
        {
            "description": "La economía es una ciencia social que estudia la producción, distribución y consumo de bienes y servicios, en últimas, a los humanos.",
            "author": "Jero Rm"
        },
        {
            "description": "La economía y la programación son dos disciplinas que se complementan, ya que ambas buscan solucionar problemas y mejorar la calidad de vida de las personas.",
            "author": "Jero Rm"
        },
        {
            "description": "La vida de un programador se basa en resolver problemas, mientras que la vida de un economista se basa en analizarlos. Ambas disciplinas buscan mejorar la calidad de vida de las personas.",
            "author": "Jero Rm"
        },
        {
            "description": "En un mundo de tecnología y economía, la mejor inversión que puedes hacer es en ti mismo. Aprende, crece y mejora cada día.",
            "author": "Jero Rm"
        }
    ]
}